MANIFEST.in
setup.cfg
setup.py
OpenGL_Demo/__init__.py
OpenGL_Demo/readme.txt
OpenGL_Demo/GLE/__init__.py
OpenGL_Demo/GLE/cone.py
OpenGL_Demo/GLE/helix.py
OpenGL_Demo/GLE/maintest.py
OpenGL_Demo/GLE/texas.py
OpenGL_Demo/GLUT/__init__.py
OpenGL_Demo/GLUT/gears.py
OpenGL_Demo/GLUT/glutplane.py
OpenGL_Demo/GLUT/gluttimerfunc_testCase.py
OpenGL_Demo/GLUT/molehill.py
OpenGL_Demo/GLUT/shader_test.py
OpenGL_Demo/GLUT/tom/__init__.py
OpenGL_Demo/GLUT/tom/arraytest.py
OpenGL_Demo/GLUT/tom/checker.py
OpenGL_Demo/GLUT/tom/cone.py
OpenGL_Demo/GLUT/tom/conechecker.py
OpenGL_Demo/GLUT/tom/conesave.py
OpenGL_Demo/GLUT/tom/logo.py
OpenGL_Demo/GLUT/tom/lorentz.py
OpenGL_Demo/GLUT/tom/test.jpg
OpenGL_Demo/GLUT/tom/text.py
OpenGL_Demo/NeHe/NeHe.bmp
OpenGL_Demo/NeHe/NeHe2.bmp
OpenGL_Demo/NeHe/Terrain.bmp
OpenGL_Demo/NeHe/Wall.bmp
OpenGL_Demo/NeHe/__init__.py
OpenGL_Demo/NeHe/lesson1.py
OpenGL_Demo/NeHe/lesson11.py
OpenGL_Demo/NeHe/lesson12.py
OpenGL_Demo/NeHe/lesson13.py
OpenGL_Demo/NeHe/lesson16.py
OpenGL_Demo/NeHe/lesson18.py
OpenGL_Demo/NeHe/lesson19.py
OpenGL_Demo/NeHe/lesson2.py
OpenGL_Demo/NeHe/lesson23.py
OpenGL_Demo/NeHe/lesson26.py
OpenGL_Demo/NeHe/lesson3.py
OpenGL_Demo/NeHe/lesson4.py
OpenGL_Demo/NeHe/lesson41.py
OpenGL_Demo/NeHe/lesson42.py
OpenGL_Demo/NeHe/lesson45.py
OpenGL_Demo/NeHe/lesson5.py
OpenGL_Demo/NeHe/lesson6-multi.py
OpenGL_Demo/NeHe/lesson6.py
OpenGL_Demo/NeHe/mirrow2.bmp
OpenGL_Demo/NeHe/myfire.jpg
OpenGL_Demo/NeHe/lesson43/Test.ttf
OpenGL_Demo/NeHe/lesson43/__init__.py
OpenGL_Demo/NeHe/lesson43/glFreeType.py
OpenGL_Demo/NeHe/lesson43/lesson43.py
OpenGL_Demo/NeHe/lesson44/__init__.py
OpenGL_Demo/NeHe/lesson44/glCamera.py
OpenGL_Demo/NeHe/lesson44/glFont.py
OpenGL_Demo/NeHe/lesson44/glPoint.py
OpenGL_Demo/NeHe/lesson44/glVector.py
OpenGL_Demo/NeHe/lesson44/lesson44.py
OpenGL_Demo/NeHe/lesson44/Art/BigGlow3.bmp
OpenGL_Demo/NeHe/lesson44/Art/Font.bmp
OpenGL_Demo/NeHe/lesson44/Art/Halo3.bmp
OpenGL_Demo/NeHe/lesson44/Art/HardGlow2.bmp
PyOpenGL_Demo.egg-info/PKG-INFO
PyOpenGL_Demo.egg-info/SOURCES.txt
PyOpenGL_Demo.egg-info/dependency_links.txt
PyOpenGL_Demo.egg-info/not-zip-safe
PyOpenGL_Demo.egg-info/requires.txt
PyOpenGL_Demo.egg-info/top_level.txt
